{
	"logger": {
		"filename": "./log/log",
		"datePattern": "yyyy-MM-dd.",
		"level": "debug"
	},
	"discord": {
		"botToken": "",
		"channelId": "",
		"ownerId": "",
		"commandPrefix": "!! ",
		"commandGroups": [
			["admin", "Admin Befehle"],
			["moderation", "Moderatoren Befehle"],
			["everyone", "Öffentliche Befehle"]
		],
		"commandGroupRoles": [
			{
				"group": "admin",
				"roles": []
			},
			{
				"group": "moderation",
				"roles": []
			}
		],
		"updateNowPlayingStatusInterval": 15000,
		"updateNextShowInterval": 60000,
		"announceNextShowTimeDifference": 900000,
		"embed": {
			"color": 6360082
		}
	},
	"google": {
		"apiKey": ""
	},
	"twitter": {
		"consumerKey": "",
		"consumerSecret": "",
		"accessTokenKey": "",
		"accessTokenSecret": "",
		"tweet": {
			"maxLength": 280
		},
		"screenName": ""
	},
	"brg": {
		"authToken": ""
	},
	"listener": {
		"message": {
			"coins": {
				"timeBetweenEvents": 60000
			}
		},
		"twitter": {
			"timeline": {
				"listenerIntervall": 60000
			}
		}
	}
}
